epivault/__init__.py
epivault/deps.py
epivault/main.py
epivault/manager.py
epivault-0.1.0.dist-info/METADATA
epivault-0.1.0.dist-info/WHEEL
epivault-0.1.0.dist-info/entry_points.txt
epivault-0.1.0.dist-info/RECORD
