Metadata-Version: 2.4
Name: epivault
Version: 0.1.0
Summary: Secure, ephemeral storage manager for Linux with YubiKey-bound LUKS2 volumes
Author-email: Imtiaz Mangerah <imtiaz_mangerah@a2d24.com>
Keywords: encryption,ephemeral,fido2,luks,security,storage,yubikey
Classifier: Development Status :: 4 - Beta
Classifier: Intended Audience :: System Administrators
Classifier: Operating System :: POSIX :: Linux
Classifier: Programming Language :: Python :: 3
Classifier: Programming Language :: Python :: 3.13
Classifier: Topic :: Security
Classifier: Topic :: System :: Filesystems
Classifier: Topic :: System :: Systems Administration
Requires-Python: >=3.13
Requires-Dist: rich>=14.3.1
Requires-Dist: typer>=0.21.1
